memory_model/__init__.py
memory_model/client.py
memory_model/types.py
memory_model-0.0.4.dist-info/METADATA
memory_model-0.0.4.dist-info/WHEEL
memory_model-0.0.4.dist-info/RECORD
